xCloudClient/__init__.py
xCloudClient/readscripts.py
xCloudClient/xcloudmanager.py
xCloudClient/resources/XCloudJDBC-2.10.6.7.jar
xCloudClient/resources/XCloudJDBC_SP_Procedure_Parser-0.1.3.jar
xCloudClient/resources/libthrift-0.9.2.jar
xCloudClient/resources/log4j-1.2.17.jar
xCloudClient/resources/lz4-1.3.0.jar
xCloudClient/resources/slf4j-api-1.7.5.jar
xCloudClient/resources/slf4j-log4j12-1.7.5.jar
xCloudClient/resources/slf4j-simple-1.7.5.jar
xCloudClient-0.1.0.dist-info/METADATA
xCloudClient-0.1.0.dist-info/WHEEL
xCloudClient-0.1.0.dist-info/top_level.txt
xCloudClient-0.1.0.dist-info/RECORD
